pyticketswitch/__init__.py
pyticketswitch/address.py
pyticketswitch/availability.py
pyticketswitch/bundle.py
pyticketswitch/callout.py
pyticketswitch/cancellation.py
pyticketswitch/card_type.py
pyticketswitch/client.py
pyticketswitch/commission.py
pyticketswitch/content.py
pyticketswitch/cost_range.py
pyticketswitch/country.py
pyticketswitch/currency.py
pyticketswitch/customer.py
pyticketswitch/debitor.py
pyticketswitch/discount.py
pyticketswitch/event.py
pyticketswitch/exceptions.py
pyticketswitch/field.py
pyticketswitch/media.py
pyticketswitch/meta.py
pyticketswitch/misc.py
pyticketswitch/mixins.py
pyticketswitch/month.py
pyticketswitch/offer.py
pyticketswitch/order.py
pyticketswitch/payment_methods.py
pyticketswitch/performance.py
pyticketswitch/price_band.py
pyticketswitch/purchase_result.py
pyticketswitch/reservation.py
pyticketswitch/review.py
pyticketswitch/seat.py
pyticketswitch/send_method.py
pyticketswitch/status.py
pyticketswitch/ticket_type.py
pyticketswitch/trolley.py
pyticketswitch/user.py
pyticketswitch/utils.py
pyticketswitch-2.14.1.dist-info/licenses/LICENSE
pyticketswitch-2.14.1.dist-info/METADATA
pyticketswitch-2.14.1.dist-info/WHEEL
pyticketswitch-2.14.1.dist-info/top_level.txt
pyticketswitch-2.14.1.dist-info/RECORD
