Metadata-Version: 2.4
Name: pyticketswitch
Version: 2.14.1
Summary: A Python interface for the Ingresso F13 API
Home-page: https://github.com/ingresso-group/pyticketswitch/
Author: Ingresso
Author-email: systems@ingresso.co.uk
License: MIT
Classifier: Development Status :: 5 - Production/Stable
Classifier: Programming Language :: Python :: 3
Classifier: Programming Language :: Python :: 2.7
Classifier: Intended Audience :: Developers
Classifier: Natural Language :: English
License-File: LICENSE
Requires-Dist: requests>=2.0.0
Requires-Dist: python-dateutil>2.5.3
Requires-Dist: six>=1.11.0
Dynamic: author
Dynamic: author-email
Dynamic: classifier
Dynamic: home-page
Dynamic: license
Dynamic: license-file
Dynamic: requires-dist
Dynamic: summary
